{
  "name": "Ancient Dragon Turtle",
  "source": "FTD",
  "page": 191,
  "size": [
    "G"
  ],
  "type": "dragon",
  "tags": [],
  "alignment": [
    "N"
  ],
  "ac": [
    "22"
  ],
  "hp": 409,
  "speed": {
    "walk": 30,
    "swim": 60
  },
  "str": 28,
  "dex": 12,
  "con": 29,
  "int": 14,
  "wis": 19,
  "cha": 15,
  "skills": {
    "perception": "+11"
  },
  "passive": 21,
  "languages": [
    "Aquan",
    "Draconic"
  ],
  "cr": "24",
  "prof_bonus": 7,
  "traits": [
    {
      "name": "Amphibious",
      "entries": [
        "The dragon turtle can breathe air and water."
      ]
    },
    {
      "name": "Blessing of the Sea (Recharges after a Short or Long Rest)",
      "entries": [
        "If the dragon turtle would be reduced to 0 hit points, its current hit point total instead resets to 350 hit points, and it recharges its Steam Breath. Additionally, the dragon turtle can now use the options in the \"Mythic Actions\" section for 1 hour. Award a party an additional 62,000 XP (124,000 XP total) for defeating the dragon turtle after its Blessing of the Sea activates."
      ]
    },
    {
      "name": "Legendary Resistance (3/Day)",
      "entries": [
        "If the dragon turtle fails a saving throw, it can choose to succeed instead."
      ]
    },
    {
      "name": "Unusual Nature",
      "entries": [
        "The dragon turtle doesn't require food or drink."
      ]
    }
  ],
  "actions": [
    {
      "name": "Multiattack",
      "entries": [
        "The dragon turtle makes one Bite or Tail attack and two Claw attacks."
      ]
    },
    {
      "name": "Bite",
      "entries": [
        "Melee atk +16 to hit, reach 15 ft., one target. 15 (1d12 + 9 damage) piercing damage plus 13 (2d12 damage) lightning damage."
      ]
    },
    {
      "name": "Claw",
      "entries": [
        "Melee atk +16 to hit, reach 15 ft., one target. 18 (2d8 + 9 damage) slashing damage."
      ]
    },
    {
      "name": "Tail",
      "entries": [
        "Melee atk +16 to hit, reach 15 ft., one target. 20 (2d10 + 9 damage) bludgeoning damage. If the target is a creature, it must succeed on a DC 24 Strength saving throw or be knocked {@condition prone}."
      ]
    },
    {
      "name": "Steam Breath {@recharge 5}",
      "entries": [
        "The dragon turtle exhales steam in a 90-foot cone. Each creature in that area must make a DC 24 Constitution saving throw, taking 67 (15d8 damage) fire damage on a failed save, or half as much damage on a successful one. Being underwater doesn't grant resistance against this damage."
      ]
    }
  ],
  "legendary": [
    {
      "name": "Attack",
      "entries": [
        "The dragon turtle makes one Claw or Tail attack."
      ]
    },
    {
      "name": "Move",
      "entries": [
        "The dragon turtle moves up to its speed. If the dragon turtle is swimming, this movement doesn't provoke opportunity attacks."
      ]
    },
    {
      "name": "Boiling Aura (Costs 3 Actions)",
      "entries": [
        "The dragon turtle radiates intense heat. Until the start of the dragon turtle's next turn, whenever a creature starts its turn within 20 feet of the dragon turtle, that creature must succeed on a {@dc 24} Constitution saving throw or take 40 ({@damage 9d8}) fire damage. Being underwater doesn't grant resistance against this damage."
      ]
    }
  ],
  "spellcasting": [],
  "conditionImmune": [
    "charmed",
    "frightened",
    "poisoned"
  ],
  "resist": [],
  "vulnerable": [],
  "immune": [
    "cold",
    "fire"
  ],
  "senses": [
    "truesight 120 ft."
  ],
  "environment": [],
  "hasToken": true,
  "hasFluff": true,
  "hasFluffImages": true
}