{
  "name": "Gegazol",
  "source": "GHLoE",
  "page": 117,
  "size": [
    "G"
  ],
  "type": "undead",
  "tags": [],
  "alignment": [
    "C",
    "E"
  ],
  "ac": [
    "22"
  ],
  "hp": 462,
  "speed": {
    "walk": 40,
    "burrow": 40,
    "fly": 80,
    "swim": 40
  },
  "str": 27,
  "dex": 14,
  "con": 26,
  "int": 16,
  "wis": 15,
  "cha": 23,
  "skills": {
    "perception": "+9"
  },
  "passive": 19,
  "languages": [
    "Draconic"
  ],
  "cr": "24",
  "prof_bonus": 7,
  "traits": [
    {
      "name": "Ice Walk",
      "entries": [
        "Gegazol can move across and climb icy surfaces without needing to make an ability check. Additionally, difficult terrain composed of ice or snow doesn't cost her extra movement."
      ]
    },
    {
      "name": "Legendary Resistance (3/Day)",
      "entries": [
        "If Gegazol fails a saving throw, she can choose to succeed instead."
      ]
    },
    {
      "name": "Magic Resistance",
      "entries": [
        "Gegazol has advantage on saving throws against spells and other magical effects."
      ]
    },
    {
      "name": "Rejuvenation",
      "entries": [
        "If destroyed while her soul vessel remains intact, Gegazol's {@condition unconscious} body rejuvenates within 5 feet of the soul vessel, where she regains 78 ({@dice 12d12}) hit points each day. When she has regained half her hit points, she regains consciousness."
      ]
    },
    {
      "name": "Stench",
      "entries": [
        "Any creature not immune to the {@condition poisoned} condition that starts its turn within 30 feet of Gegazol must succeed on a {@dc 23} Constitution saving throw or become {@condition poisoned} until the start of that creature's next turn. On a successful saving throw, the creature is immune to Gegazol's stench for 1 hour."
      ]
    },
    {
      "name": "Turning Defiance",
      "entries": [
        "Gegazol and undead within 120 feet of her have advantage on saving throws against effects that turn undead."
      ]
    }
  ],
  "actions": [
    {
      "name": "Multiattack",
      "entries": [
        "Gegazol can use her frightful presence. She then makes three attacks: one with her bite and two with her claws."
      ]
    },
    {
      "name": "Bite",
      "entries": [
        "Melee atk +15 to hit, reach 15 ft., one target. 21 (2d12 + 8 damage) piercing damage, 9 (2d8 damage) cold damage and 9 (2d8 damage) necrotic damage."
      ]
    },
    {
      "name": "Claw",
      "entries": [
        "Melee atk +15 to hit, reach 10 ft., one target. 19 (2d10 + 8 damage) piercing damage."
      ]
    },
    {
      "name": "Tail",
      "entries": [
        "Melee atk +15 to hit, reach 20 ft., one target. 19 (2d10 + 8 damage) bludgeoning damage. If the target is a creature, it must succeed on a DC 23 Strength saving throw or fall {@condition prone}."
      ]
    },
    {
      "name": "Frightful Presence",
      "entries": [
        "Each creature of Gegazol's choice within 120 feet of and aware of her must succeed on a DC 21 Wisdom saving throw or become {@condition frightened} for 1 minute. A creature can repeat the saving throw at the end of each of its turns, ending the effect on itself on a success. If a creature's saving throw is successful or the effect ends for it, the creature is immune to Gegazol's Frightful Presence for the next 24 hours."
      ]
    },
    {
      "name": "Breath of Long Night {@recharge 5}",
      "entries": [
        "Gegazol exhales frozen material and rot in a 90-foot cone. Each creature in that area must make a DC 23 Constitution saving throw, taking 45 (10d8 damage) cold damage and 45 (10d8 damage) necrotic damage on a failed save, or half as much damage on a successful one. Those who fail the save also gain two levels of {@condition exhaustion} until the end of Gegazol's next turn, and those who fail by 5 or more are also {@condition blinded} for 1 minute. A {@condition blinded} creature can repeat the saving throw at the end of each of its turns, ending the effect on itself on a success."
      ]
    }
  ],
  "legendary": [
    {
      "name": "Daemon Sight",
      "entries": [
        "Gegazol gains truesight out to 120 feet until the end of her next turn and can make a Wisdom (Perception) check."
      ]
    },
    {
      "name": "Tail",
      "entries": [
        "Gegazol makes a tail attack."
      ]
    },
    {
      "name": "Wings of Winter (Costs 2 Actions)",
      "entries": [
        "Gegazol beats her wings. Each creature within 30 feet of her must succeed on a {@dc 23} Dexterity saving throw or take 17 ({@damage 2d8 + 8}) bludgeoning damage and 9 ({@damage 2d8}) cold damage, and then fall {@condition prone}. Gegazol can then fly up to half her flying speed."
      ]
    }
  ],
  "spellcasting": [],
  "conditionImmune": [
    "charmed",
    "exhaustion",
    "frightened",
    "paralyzed",
    "poisoned"
  ],
  "resist": [],
  "vulnerable": [],
  "immune": [
    "cold",
    "necrotic",
    "poison"
  ],
  "senses": [
    "blindsight 60 ft.",
    "darkvision 120 ft."
  ],
  "environment": [],
  "hasToken": true,
  "hasFluff": true,
  "hasFluffImages": true
}