{
  "name": "Jandar Chergoba",
  "source": "WDH",
  "page": 116,
  "size": [
    "M"
  ],
  "type": "humanoid",
  "tags": [
    "tiefling"
  ],
  "alignment": [
    "L",
    "E"
  ],
  "ac": [
    "13"
  ],
  "hp": 33,
  "speed": {
    "walk": 30
  },
  "str": 11,
  "dex": 14,
  "con": 12,
  "int": 10,
  "wis": 13,
  "cha": 14,
  "skills": {
    "deception": "+4",
    "persuasion": "+4",
    "religion": "+2"
  },
  "passive": 11,
  "languages": [
    "Common",
    "Infernal"
  ],
  "cr": "2",
  "prof_bonus": 2,
  "traits": [
    {
      "name": "Dark Devotion",
      "entries": [
        "Jandar has advantage on saving throws against being {@condition charmed} or {@condition frightened}."
      ]
    }
  ],
  "actions": [
    {
      "name": "Multiattack",
      "entries": [
        "Jandar makes two melee attacks."
      ]
    },
    {
      "name": "Dagger",
      "entries": [
        "Melee atk +4 to hit, reach 5 ft., one creature. 4 (1d4 + 2 damage) piercing damage. Or Ranged Weapon Attack: +4 to hit, range 20/60 ft., one creature. 4 (1d4 + 2 damage) piercing damage."
      ]
    }
  ],
  "legendary": [],
  "spellcasting": [
    {
      "name": "Innate Spellcasting",
      "headerEntries": [
        "Jandar's spellcasting ability is Charisma. He can innately cast the following spells, requiring no material components:"
      ],
      "will": [
        "thaumaturgy"
      ],
      "ability": "cha",
      "spells": {
        "0": {
          "spells": []
        },
        "1": {
          "spells": []
        },
        "2": {
          "spells": []
        },
        "3": {
          "spells": []
        },
        "4": {
          "spells": []
        },
        "5": {
          "spells": []
        },
        "6": {
          "spells": []
        },
        "7": {
          "spells": []
        },
        "8": {
          "spells": []
        },
        "9": {
          "spells": []
        }
      },
      "daily": {
        "1": []
      }
    }
  ],
  "conditionImmune": [],
  "resist": [
    "fire"
  ],
  "vulnerable": [],
  "immune": [],
  "senses": [
    "darkvision 60 ft."
  ],
  "environment": [],
  "hasToken": true,
  "hasFluff": true,
  "hasFluffImages": false
}